{
  "textures": {
    "sides": "appliedenergistics2:parts/monitor_sides_status",
    "staticSides": "appliedenergistics2:parts/export_bus_sides",
    "back": "appliedenergistics2:parts/transition_plane_back",
    "particle": "appliedenergistics2:parts/transition_plane_back",
    "front": "appliedintegrations:blocks/parts/energy.annihilation.face"
  },
  "elements": [
    {
      "from": [
        5,
        5,
        1
      ],
      "to": [
        11,
        11,
        2
      ],
      "faces": {
        "east": {
          "texture": "#sides"
        },
        "south": {
          "texture": "#back"
        },
        "west": {
          "texture": "#sides"
        },
        "up": {
          "texture": "#sides"
        },
        "down": {
          "texture": "#sides"
        }
      }
    },{
      "from": [
        15,
        15,
        0
      ],
      "to": [
        1,
        1,
        1
      ],
      "faces": {
        "down": {
          "texture": "#staticSides"
        },
        "up": {
          "texture": "#staticSides"
        },
        "north": {
          "texture": "#front"
        },
        "east": {
          "texture": "#staticSides"
        },
        "south": {
          "texture": "#back"
        },
        "west": {
          "texture": "#staticSides"
        }
      }
    }
  ]
}